dynrender-0.1.8.dist-info/METADATA
dynrender-0.1.8.dist-info/WHEEL
dynrender-0.1.8.dist-info/licenses/LICENSE
dynrender/Core.py
dynrender/DynAdditional.py
dynrender/DynConfig.py
dynrender/DynHeader.py
dynrender/DynMajor.py
dynrender/DynRepost.py
dynrender/DynStyle.py
dynrender/DynText.py
dynrender/DynTools.py
dynrender/Static.zip
dynrender/__init__.py
dynrender-0.1.8.dist-info/RECORD
