Metadata-Version: 2.1
Name: dynrender
Version: 0.1.8
Summary: 使用skia-python将BiliBili动态渲染为图片
Author-Email: BalconyJH <balconyjh@gmail.com>, DMC <lzxder@outlook.com>
License: GNU GPLv3
Requires-Python: <4.0,>=3.8
Requires-Dist: skia-python<88.0,>=87.5
Requires-Dist: httpx<1.0.0,>=0.24.1
Requires-Dist: emoji<3.0.0,>=2.6.0
Requires-Dist: dynamicadaptor<1.0.0,>=0.4.9
